{
  "id": "expected-pco2-winters",
  "name": "Expected PCO2 (Winters)",
  "status": "active",
  "complexity": "simple",
  "inputs": [
    {
      "type": "numeric",
      "id": "f1",
      "label": "f1"
    }
  ],
  "outputs": [
    {
      "type": "numeric",
      "id": "o1",
      "label": "o1",
      "formula": "1.5 * f1 + 8",
      "precision": 2,
      "defaultUnit": "mmHg"
    },
    {
      "type": "numeric",
      "id": "lower",
      "label": "Lower:",
      "formula": "o1 - 2",
      "precision": 2,
      "defaultUnit": "mmHg"
    },
    {
      "type": "numeric",
      "id": "upper",
      "label": "Upper:",
      "formula": "o1 + 2",
      "precision": 2,
      "defaultUnit": "mmHg"
    }
  ],
  "version": 1,
  "createdAt": "2026-03-06T14:19:02.195Z",
  "updatedAt": "2026-03-06T14:19:02.195Z"
}