{
  "id": "fract-excr-of-ca-feca",
  "name": "Fract Excr of Ca (FECa)",
  "status": "active",
  "complexity": "moderate",
  "inputs": [
    {
      "type": "numeric",
      "id": "pi_calcium",
      "label": "PI Calcium"
    },
    {
      "type": "numeric",
      "id": "pi_creatinine",
      "label": "PI Creatinine"
    },
    {
      "type": "numeric",
      "id": "u_calcium",
      "label": "U Calcium"
    },
    {
      "type": "numeric",
      "id": "u_creatinine",
      "label": "U Creatinine"
    }
  ],
  "outputs": [
    {
      "type": "numeric",
      "id": "f_e_ca",
      "label": "F.E. Ca",
      "formula": "u_calcium * pi_creatinine / (u_creatinine * pi_calcium)",
      "precision": 2,
      "defaultUnit": "%"
    }
  ],
  "version": 1,
  "createdAt": "2026-03-06T14:19:02.207Z",
  "updatedAt": "2026-03-06T14:19:02.207Z"
}